setup.py
Maxis_EA_Messenger_Client.egg-info/PKG-INFO
Maxis_EA_Messenger_Client.egg-info/SOURCES.txt
Maxis_EA_Messenger_Client.egg-info/dependency_links.txt
Maxis_EA_Messenger_Client.egg-info/requires.txt
Maxis_EA_Messenger_Client.egg-info/top_level.txt
client/__init__.py
client/client.py
client/clients/__init__.py
client/clients/add_contact.py
client/clients/client_windows.py
client/clients/client_windows2(bakup).py
client/clients/database.py
client/clients/del_contact.py
client/clients/main_windows.py
client/clients/start_dialog.py
client/clients/transport.py
client/common/__init__.py
client/common/decorate.py
client/common/descriptor.py
client/common/errors.py
client/common/metaclasses.py
client/common/utils.py
client/common/variables.py
client/logger/__init__.py
client/logger/log_client.py