Metadata-Version: 1.0
Name: Maxis-EA-Messenger-Client
Version: 0.0.1
Summary: Messenger_Client
Home-page: UNKNOWN
Author: Maxim Baranov
Author-email: maxis@ya.ru
License: UNKNOWN
Platform: UNKNOWN
